makehlp/__init__.py
makehlp/main.py
makehlp-0.1.2.dist-info/METADATA
makehlp-0.1.2.dist-info/WHEEL
makehlp-0.1.2.dist-info/entry_points.txt
makehlp-0.1.2.dist-info/RECORD
