Metadata-Version: 2.4
Name: makehlp
Version: 0.1.2
Summary: makehlp
Project-URL: Homepage, https://github.com/personalcomputer/makehlp
Author-email: John Miller <john@johngm.com>
Classifier: License :: OSI Approved :: MIT License
Classifier: Programming Language :: Python
Classifier: Programming Language :: Python :: 3
Classifier: Programming Language :: Python :: Implementation :: CPython
Requires-Python: >=3.11
